app.py
AUTO_GMAI_GENERATION-0.0.1.dist-info/LICENSE
AUTO_GMAI_GENERATION-0.0.1.dist-info/METADATA
AUTO_GMAI_GENERATION-0.0.1.dist-info/WHEEL
AUTO_GMAI_GENERATION-0.0.1.dist-info/top_level.txt
AUTO_GMAI_GENERATION-0.0.1.dist-info/RECORD
