Metadata-Version: 2.1
Name: AUTO-GMAI-GENERATION
Version: 0.0.1
Summary: AUTO CREATE mAIL
Project-URL: Homepage, https://github.com/Sz3RO/Auto-Mail-Genaration
Requires-Python: >=3.7
License-File: LICENSE
